tidysorter/__init__.py
tidysorter/constants.py
tidysorter/generate.py
tidysorter/tidysorter.py
tidysorter/utils.py
tidysorter/zip.py
tidysorter-1.0.5.dist-info/LICENSE
tidysorter-1.0.5.dist-info/METADATA
tidysorter-1.0.5.dist-info/WHEEL
tidysorter-1.0.5.dist-info/entry_points.txt
tidysorter-1.0.5.dist-info/top_level.txt
tidysorter-1.0.5.dist-info/RECORD
