Metadata-Version: 2.1
Name: tidysorter
Version: 1.0.5
Summary: A tool to organize files in a directory
Home-page: https://github.com/ale-floc/tidysorter
Author: Arnaud Le Floch
Author-email: a.lefloch2491@gmail.com
License-File: LICENSE
